README.txt
dev.cfg
sample-prod.cfg
setup.py
start-zoner.py
test.cfg
zoner_users.py
locales/messages.pot
locales/de/LC_MESSAGES/messages.mo
locales/de/LC_MESSAGES/messages.po
zoner/__init__.py
zoner/better_flash.py
zoner/breadcrumb_widget.py
zoner/commands.py
zoner/controllers.py
zoner/expanding_form.py
zoner/json.py
zoner/model.py
zoner/release.py
zoner/soa_form.py
zoner/user_manage.py
zoner.egg-info/PKG-INFO
zoner.egg-info/SOURCES.txt
zoner.egg-info/dependency_links.txt
zoner.egg-info/entry_points.txt
zoner.egg-info/not-zip-safe
zoner.egg-info/requires.txt
zoner.egg-info/top_level.txt
zoner/config/__init__.py
zoner/config/app.cfg
zoner/config/log.cfg
zoner/static/css/style.css
zoner/static/images/alert.png
zoner/static/images/favicon.ico
zoner/static/images/header_inner.png
zoner/static/images/info.png
zoner/static/images/ok.png
zoner/static/images/python-powered-w-100x40.png
zoner/static/images/tg_under_the_hood.png
zoner/static/images/under_the_hood_blue.png
zoner/templates/__init__.py
zoner/templates/about.kid
zoner/templates/editsoa.kid
zoner/templates/editzone.kid
zoner/templates/fixed_list_form.kid
zoner/templates/history.kid
zoner/templates/history_record.kid
zoner/templates/login.kid
zoner/templates/managezone.kid
zoner/templates/master.kid
zoner/templates/revert.kid
zoner/templates/soa_tabletemplate.kid
zoner/templates/welcome.kid
zoner/templates/zones.kid
zoner/tests/__init__.py
zoner/tests/test_controllers.py
zoner/tests/test_model.py
zoner/tests/utils_database.py