Metadata-Version: 1.0
Name: zoner
Version: 1.4.0
Summary: A DNS zone management web application.
Home-page: http://pypi.python.org/pypi/zoner/
Author: Chris Miles
Author-email: miles.chris@gmail.com
License: MIT
Download-URL: http://pypi.python.org/pypi/zoner/
Keywords: turbogears.app
Platform: UNKNOWN
Classifier: Development Status :: 4 - Beta
Classifier: Operating System :: OS Independent
Classifier: Programming Language :: Python
Classifier: Topic :: Internet :: Name Service (DNS)
Classifier: Topic :: Software Development :: Libraries :: Python Modules
Classifier: Topic :: System :: Systems Administration
Classifier: Intended Audience :: System Administrators
Classifier: Framework :: TurboGears
Classifier: Framework :: TurboGears :: Applications
